setup.py
awsf_distributions/Binomialdistribution_challenge.py
awsf_distributions/Gaussiandistribution.py
awsf_distributions/Generaldistribution.py
awsf_distributions/__init__.py
awsf_distributions.egg-info/PKG-INFO
awsf_distributions.egg-info/SOURCES.txt
awsf_distributions.egg-info/dependency_links.txt
awsf_distributions.egg-info/not-zip-safe
awsf_distributions.egg-info/top_level.txt