Metadata-Version: 2.1
Name: awsf-distributions
Version: 0.1
Summary: Binomial distributions and Gaussian distributions
Home-page: UNKNOWN
License: UNKNOWN
Platform: UNKNOWN
